ZetcodeSymfonyJiaochengChuyi/README.md
ZetcodeSymfonyJiaochengChuyi/__init__.py
ZetcodeSymfonyJiaochengChuyi/__main__.py
ZetcodeSymfonyJiaochengChuyi/file.epub
ZetcodeSymfonyJiaochengChuyi/index.html
ZetcodeSymfonyJiaochengChuyi/css/__init__.py
ZetcodeSymfonyJiaochengChuyi/css/annotations.css
ZetcodeSymfonyJiaochengChuyi/css/main.css
ZetcodeSymfonyJiaochengChuyi/css/normalize.css
ZetcodeSymfonyJiaochengChuyi/css/popup.css
ZetcodeSymfonyJiaochengChuyi/font/__init__.py
ZetcodeSymfonyJiaochengChuyi/font/fontello.eot
ZetcodeSymfonyJiaochengChuyi/font/fontello.svg
ZetcodeSymfonyJiaochengChuyi/font/fontello.ttf
ZetcodeSymfonyJiaochengChuyi/font/fontello.woff
ZetcodeSymfonyJiaochengChuyi/img/__init__.py
ZetcodeSymfonyJiaochengChuyi/img/annotator-glyph-sprite.png
ZetcodeSymfonyJiaochengChuyi/img/annotator-icon-sprite.png
ZetcodeSymfonyJiaochengChuyi/img/apple-touch-icon.png
ZetcodeSymfonyJiaochengChuyi/img/cancelfullscreen.png
ZetcodeSymfonyJiaochengChuyi/img/close.png
ZetcodeSymfonyJiaochengChuyi/img/fullscreen.png
ZetcodeSymfonyJiaochengChuyi/img/loader.gif
ZetcodeSymfonyJiaochengChuyi/img/menu-icon.png
ZetcodeSymfonyJiaochengChuyi/img/save.png
ZetcodeSymfonyJiaochengChuyi/img/saved.png
ZetcodeSymfonyJiaochengChuyi/img/settings-s.png
ZetcodeSymfonyJiaochengChuyi/img/settings.png
ZetcodeSymfonyJiaochengChuyi/img/star.png
ZetcodeSymfonyJiaochengChuyi/js/__init__.py
ZetcodeSymfonyJiaochengChuyi/js/epub.js
ZetcodeSymfonyJiaochengChuyi/js/epub.min.js
ZetcodeSymfonyJiaochengChuyi/js/epub.min.map
ZetcodeSymfonyJiaochengChuyi/js/hooks.min.js
ZetcodeSymfonyJiaochengChuyi/js/hooks.min.map
ZetcodeSymfonyJiaochengChuyi/js/reader.js
ZetcodeSymfonyJiaochengChuyi/js/reader.js.map
ZetcodeSymfonyJiaochengChuyi/js/reader.min.js
ZetcodeSymfonyJiaochengChuyi/js/reader.min.map
ZetcodeSymfonyJiaochengChuyi/js/hooks/__init__.py
ZetcodeSymfonyJiaochengChuyi/js/hooks/extensions/__init__.py
ZetcodeSymfonyJiaochengChuyi/js/hooks/extensions/highlight.js
zetcode_symfony_jiaocheng_chuyi-2024.3.5.0.dist-info/METADATA
zetcode_symfony_jiaocheng_chuyi-2024.3.5.0.dist-info/WHEEL
zetcode_symfony_jiaocheng_chuyi-2024.3.5.0.dist-info/entry_points.txt
zetcode_symfony_jiaocheng_chuyi-2024.3.5.0.dist-info/top_level.txt
zetcode_symfony_jiaocheng_chuyi-2024.3.5.0.dist-info/RECORD
